<?xml version="1.0" encoding="utf-8"?>
<doctrine-mapping xmlns="http://doctrine-project.org/schemas/orm/doctrine-mapping" xmlns:xsi="http://www.w3.org/2001/XMLSchema-instance" xsi:schemaLocation="http://doctrine-project.org/schemas/orm/doctrine-mapping http://doctrine-project.org/schemas/orm/doctrine-mapping.xsd">

    <entity name="App\CoreBundle\Entity\BuildLog" table="build_log">
        <id name="id" type="integer" column="id">
            <generator strategy="AUTO"/>
        </id>

        <field name="message" column="message" type="text" nullable="true" />
        <field name="type" column="type" type="string" length="255" />
        <field name="stream" column="stream" type="string" length="255" nullable="true" />
        <field name="createdAt" column="created_at" type="datetime" />
        <field name="updatedAt" column="updated_at" type="datetime" />

        <many-to-one field="build" target-entity="App\CoreBundle\Entity\Build" inversed-by="logs">
            <join-column name="build_id" referenced-column-name="id" />
            <cascade><cascade-remove /></cascade>
        </many-to-one>
    </entity>

</doctrine-mapping>
